pocket/__init__.py
pocket/__main__.py
pocket/app.py
pocket/import_ssh.py
ssh_pocket-1.2.2.dist-info/LICENSE
ssh_pocket-1.2.2.dist-info/METADATA
ssh_pocket-1.2.2.dist-info/WHEEL
ssh_pocket-1.2.2.dist-info/entry_points.txt
ssh_pocket-1.2.2.dist-info/top_level.txt
ssh_pocket-1.2.2.dist-info/RECORD
